bibrecord/__init__.py
bibrecord/bibtex.py
bibrecord/database.py
bibrecord/record.py
bibrecord-0.2.2.dist-info/LICENSE
bibrecord-0.2.2.dist-info/METADATA
bibrecord-0.2.2.dist-info/WHEEL
bibrecord-0.2.2.dist-info/top_level.txt
bibrecord-0.2.2.dist-info/RECORD
