Metadata-Version: 2.1
Name: bibrecord
Version: 0.2.2
Summary: Handling bibliographic records within source code
Home-page: 
Author: Till Biskup
Author-email: till@till-biskup.de
License: BSD
Project-URL: Documentation, https://bibrecord.docs.till-biskup.de/
Project-URL: Source, https://github.com/tillbiskup/bibrecord
Keywords: bibliography,bibtex,literature,cite,references
Classifier: Programming Language :: Python :: 3
Classifier: Programming Language :: Python :: 3.7
Classifier: Programming Language :: Python :: 3.8
Classifier: Programming Language :: Python :: 3.9
Classifier: Programming Language :: Python :: 3.10
Classifier: Programming Language :: Python :: 3.11
Classifier: Programming Language :: Python :: 3.12
Classifier: License :: OSI Approved :: BSD License
Classifier: Operating System :: OS Independent
Classifier: Intended Audience :: Science/Research
Classifier: Development Status :: 4 - Beta
Requires-Python: >=3.7
License-File: LICENSE
Provides-Extra: deployment
Requires-Dist: build ; extra == 'deployment'
Requires-Dist: twine ; extra == 'deployment'
Provides-Extra: dev
Requires-Dist: prospector ; extra == 'dev'
Requires-Dist: pyroma ; extra == 'dev'
Requires-Dist: bandit ; extra == 'dev'
Requires-Dist: black ; extra == 'dev'
Requires-Dist: pymetacode ; extra == 'dev'
Provides-Extra: docs
Requires-Dist: sphinx ; extra == 'docs'
Requires-Dist: sphinx-rtd-theme ; extra == 'docs'
Requires-Dist: sphinx-multiversion ; extra == 'docs'
